[
    {
        "Status": null,
        "Company": null,
        "Experiences": [
            {
                "Job Occupation": null,
                "Job Type": null,
                "Previous Experiences": null,
                "Job Length": null,
                "Job Desc": null
            }
        ],
        "First Name": null,
        "Concentration": null,
        "userid": "d11f1d6a-0250-418b-b48a-335e9e791bf6",
        "Grade Level": null,
        "School": null,
        "Major": null,
        "Username": "JohnDoe_xd",
        "Skills": null,
        "GPA": null,
        "Minor": null,
        "Last Name": null,
        "Phone Number": null,
        "Extra-Cirriculars": null,
        "Account Type": "Administrator",
        "Password": "JavaIsCool",
        "Email Address": null
    },
    {
        "Status": "Unemployed",
        "Company": null,
        "Experiences": [
            {
                "Job Occupation": null,
                "Job Type": null,
                "Previous Experiences": null,
                "Job Length": null,
                "Job Desc": null
            }
        ],
        "First Name": "John",
        "Concentration": "Computer Science",
        "userid": "f9808985-8d9a-4d42-866e-cd79c08faf41",
        "Grade Level": "Junior",
        "School": "University of South Carolina",
        "Major": "Computer Information Systems",
        "Username": "JackMiller",
        "Skills": [
            "Java",
            "mySQL",
            "C++",
            "MTA:Networking Fundamentals"
        ],
        "GPA": "3.4",
        "Minor": null,
        "Last Name": "Doe",
        "Phone Number": null,
        "Extra-Cirriculars": [
            "Robotics"
        ],
        "Account Type": "Student",
        "Password": "INeedAJob",
        "Email Address": null
    },
    {
        "Status": null,
        "Company": "Volt-tech",
        "Experiences": [
            {
                "Job Occupation": null,
                "Job Type": null,
                "Previous Experiences": null,
                "Job Length": null,
                "Job Desc": null
            }
        ],
        "First Name": null,
        "Concentration": null,
        "userid": "4658370a-83c4-4987-b3ea-9e948f65338e",
        "Grade Level": null,
        "School": null,
        "Major": null,
        "Username": "JeffreySmith",
        "Skills": null,
        "GPA": null,
        "Minor": null,
        "Last Name": null,
        "Phone Number": null,
        "Extra-Cirriculars": null,
        "Account Type": "Employer",
        "Password": "needNewHires!",
        "Email Address": null
    },
    {
        "Status": null,
        "Company": null,
        "Experiences": [
            {
                "Job Occupation": null,
                "Job Type": null,
                "Previous Experiences": null,
                "Job Length": null,
                "Job Desc": null
            }
        ],
        "First Name": null,
        "Concentration": null,
        "userid": "084ef88a-1dc8-45e6-8561-dc84c6b11cb2",
        "Grade Level": null,
        "School": null,
        "Major": null,
        "Username": "bjj",
        "Skills": null,
        "GPA": null,
        "Minor": null,
        "Last Name": null,
        "Phone Number": "999-9999",
        "Extra-Cirriculars": null,
        "Account Type": "Student",
        "Password": "dfsfafasd",
        "Email Address": "btj2@email.sc.edu"
    },
    {
        "Status": null,
        "Company": null,
        "Experiences": [
            {
                "Job Occupation": null,
                "Job Type": null,
                "Previous Experiences": null,
                "Job Length": null,
                "Job Desc": null
            }
        ],
        "First Name": null,
        "Concentration": null,
        "userid": "4aa6c49f-ce8a-4216-bc4f-4c58fac6de16",
        "Grade Level": null,
        "School": null,
        "Major": null,
        "Username": "brady smoak",
        "Skills": null,
        "GPA": null,
        "Minor": null,
        "Last Name": null,
        "Phone Number": "999-9999",
        "Extra-Cirriculars": null,
        "Account Type": "Student",
        "Password": "celtics rule",
        "Email Address": "btj2@email.sc.edu"
    },
    {
        "Status": null,
        "Company": null,
        "Experiences": [
            {
                "Job Occupation": null,
                "Job Type": null,
                "Previous Experiences": null,
                "Job Length": null,
                "Job Desc": null
            }
        ],
        "First Name": "brandon",
        "Concentration": "CS",
        "userid": "e739baab-e651-4fa7-a592-fff4a75be554",
        "Grade Level": "senior",
        "School": "u of sc",
        "Major": "CIS",
        "Username": "brandon",
        "Skills": [],
        "GPA": "3.8",
        "Minor": "BIM",
        "Last Name": "jennings",
        "Phone Number": "999-9999",
        "Extra-Cirriculars": [],
        "Account Type": "Student",
        "Password": "1234",
        "Email Address": "rockstar@email.com"
    },
    {
        "Status": null,
        "Company": "brandon",
        "Experiences": [
            {
                "Job Occupation": null,
                "Job Type": null,
                "Previous Experiences": null,
                "Job Length": null,
                "Job Desc": null
            }
        ],
        "First Name": null,
        "Concentration": null,
        "userid": "797fb926-3601-44db-b8c2-68a5afd84222",
        "Grade Level": null,
        "School": null,
        "Major": null,
        "Username": "btj",
        "Skills": null,
        "GPA": null,
        "Minor": null,
        "Last Name": "jennings",
        "Phone Number": null,
        "Extra-Cirriculars": null,
        "Account Type": "Student",
        "Password": "1234",
        "Email Address": null
    },
    {
        "Status": null,
        "Company": null,
        "Experiences": [
            {
                "Job Occupation": null,
                "Job Type": null,
                "Previous Experiences": null,
                "Job Length": null,
                "Job Desc": null
            }
        ],
        "First Name": "adam",
        "Concentration": "a",
        "userid": "380dcbfa-beff-4815-b66c-4df5f6c9fc4d",
        "Grade Level": "a",
        "School": "a",
        "Major": "a",
        "Username": "adamrt",
        "Skills": null,
        "GPA": "a",
        "Minor": "a",
        "Last Name": "a",
        "Phone Number": null,
        "Extra-Cirriculars": null,
        "Account Type": "Student",
        "Password": "adam",
        "Email Address": null
    },
    {
        "Status": null,
        "Company": null,
        "Experiences": [
            {
                "Job Occupation": null,
                "Job Type": null,
                "Previous Experiences": null,
                "Job Length": null,
                "Job Desc": null
            }
        ],
        "First Name": "adam",
        "Concentration": "a",
        "userid": "432fafc9-ca11-4edf-96e7-3e9bc263d782",
        "Grade Level": "a",
        "School": "a",
        "Major": "a",
        "Username": "adamrt",
        "Skills": null,
        "GPA": "a",
        "Minor": "a",
        "Last Name": "a",
        "Phone Number": null,
        "Extra-Cirriculars": null,
        "Account Type": "Student",
        "Password": "adam",
        "Email Address": null
    },
    {
        "Status": null,
        "Company": null,
        "Experiences": [
            {
                "Job Occupation": null,
                "Job Type": null,
                "Previous Experiences": null,
                "Job Length": null,
                "Job Desc": null
            }
        ],
        "First Name": "adam",
        "Concentration": null,
        "userid": "d091da5a-3295-420f-96ac-c14346e8f6de",
        "Grade Level": null,
        "School": null,
        "Major": null,
        "Username": "aaaaaaa",
        "Skills": null,
        "GPA": null,
        "Minor": null,
        "Last Name": "adam",
        "Phone Number": null,
        "Extra-Cirriculars": null,
        "Account Type": "Student",
        "Password": "adam",
        "Email Address": null
    },
    {
        "Status": null,
        "Company": null,
        "Experiences": [
            {
                "Job Occupation": null,
                "Job Type": null,
                "Previous Experiences": null,
                "Job Length": null,
                "Job Desc": null
            }
        ],
        "First Name": null,
        "Concentration": null,
        "userid": "ff38ee73-c5c5-4b7d-a0c7-b293b5f98e4f",
        "Grade Level": null,
        "School": null,
        "Major": null,
        "Username": "employerman",
        "Skills": null,
        "GPA": null,
        "Minor": null,
        "Last Name": null,
        "Phone Number": null,
        "Extra-Cirriculars": null,
        "Account Type": "Employer",
        "Password": "adam",
        "Email Address": null
    },
    {
        "Status": null,
        "Company": null,
        "Experiences": [
            {
                "Job Occupation": null,
                "Job Type": null,
                "Previous Experiences": null,
                "Job Length": null,
                "Job Desc": null
            }
        ],
        "First Name": "Adam",
        "Concentration": null,
        "userid": "4751b40f-1df7-4f33-b27b-778a3b3fd511",
        "Grade Level": null,
        "School": null,
        "Major": null,
        "Username": "adammmm",
        "Skills": null,
        "GPA": null,
        "Minor": null,
        "Last Name": "Trickett",
        "Phone Number": null,
        "Extra-Cirriculars": null,
        "Account Type": "Student",
        "Password": "adam",
        "Email Address": null
    },
    {
        "Status": null,
        "Company": null,
        "Experiences": [
            {
                "Job Occupation": null,
                "Job Type": null,
                "Previous Experiences": null,
                "Job Length": null,
                "Job Desc": null
            }
        ],
        "First Name": null,
        "Concentration": null,
        "userid": "40567560-4e02-4736-a9de-701c5e8af624",
        "Grade Level": null,
        "School": null,
        "Major": null,
        "Username": "adamemp",
        "Skills": [],
        "GPA": null,
        "Minor": null,
        "Last Name": null,
        "Phone Number": null,
        "Extra-Cirriculars": [],
        "Account Type": "Employer",
        "Password": "adam",
        "Email Address": null
    },
    {
        "Status": null,
        "Company": null,
        "Experiences": [
            {
                "Job Occupation": null,
                "Job Type": null,
                "Previous Experiences": null,
                "Job Length": null,
                "Job Desc": null
            }
        ],
        "First Name": null,
        "Concentration": null,
        "userid": "0cf216ec-8329-4902-b81d-331c45992d4b",
        "Grade Level": null,
        "School": null,
        "Major": null,
        "Username": "adamwork",
        "Skills": [],
        "GPA": null,
        "Minor": null,
        "Last Name": null,
        "Phone Number": null,
        "Extra-Cirriculars": [],
        "Account Type": "Employer",
        "Password": "adam",
        "Email Address": null
    },
    {
        "Status": null,
        "Company": "adamco",
        "Experiences": [
            {
                "Job Occupation": null,
                "Job Type": null,
                "Previous Experiences": null,
                "Job Length": null,
                "Job Desc": null
            }
        ],
        "First Name": "adam",
        "Concentration": null,
        "userid": "c88ad49c-2579-4b83-9dbd-cdae6a597dfd",
        "Grade Level": null,
        "School": null,
        "Major": null,
        "Username": "adamusername",
        "Skills": [],
        "GPA": null,
        "Minor": null,
        "Last Name": "trickett",
        "Phone Number": null,
        "Extra-Cirriculars": [],
        "Account Type": "Employer",
        "Password": "adampassword",
        "Email Address": null
    },
    {
        "Status": null,
        "Company": "Trickett",
        "Experiences": [
            {
                "Job Occupation": null,
                "Job Type": null,
                "Previous Experiences": null,
                "Job Length": null,
                "Job Desc": null
            }
        ],
        "First Name": null,
        "Concentration": null,
        "userid": "eb611ec0-850a-4a7e-9b08-9579859fd2eb",
        "Grade Level": null,
        "School": "Adam",
        "Major": null,
        "Username": "adamstudent",
        "Skills": [
            "Python",
            "Java",
            "C++",
            "Window cleaning",
            "Floor cleaning"
        ],
        "GPA": null,
        "Minor": null,
        "Last Name": null,
        "Phone Number": null,
        "Extra-Cirriculars": [
            "Cleaning club",
            "Coding club",
            ""
        ],
        "Account Type": "Student",
        "Password": "adam",
        "Email Address": null
    },
    {
        "Status": null,
        "Company": "trickett",
        "Experiences": [
            {
                "Job Occupation": null,
                "Job Type": null,
                "Previous Experiences": null,
                "Job Length": null,
                "Job Desc": null
            }
        ],
        "First Name": null,
        "Concentration": null,
        "userid": "02a59df5-f209-44d8-8d50-110eb129ae2f",
        "Grade Level": null,
        "School": "adam",
        "Major": null,
        "Username": "studenttest",
        "Skills": [
            "counseling"
        ],
        "GPA": null,
        "Minor": null,
        "Last Name": null,
        "Phone Number": null,
        "Extra-Cirriculars": [
            "camping"
        ],
        "Account Type": "Student",
        "Password": "adam",
        "Email Address": null
    },
    {
        "Status": null,
        "Company": null,
        "Experiences": [
            {
                "Job Occupation": null,
                "Job Type": null,
                "Previous Experiences": null,
                "Job Length": null,
                "Job Desc": null
            }
        ],
        "First Name": "a",
        "Concentration": null,
        "userid": "9296fb6f-c534-45ed-80d7-18bcb5257441",
        "Grade Level": null,
        "School": null,
        "Major": null,
        "Username": "1",
        "Skills": [],
        "GPA": null,
        "Minor": null,
        "Last Name": "a",
        "Phone Number": null,
        "Extra-Cirriculars": [],
        "Account Type": "Student",
        "Password": "a",
        "Email Address": null
    },
    {
        "Status": null,
        "Company": null,
        "Experiences": [
            {
                "Job Occupation": null,
                "Job Type": null,
                "Previous Experiences": null,
                "Job Length": null,
                "Job Desc": null
            }
        ],
        "First Name": "a",
        "Concentration": null,
        "userid": "ce240856-b751-4bbd-9ef3-ad7e87d3ae23",
        "Grade Level": null,
        "School": null,
        "Major": null,
        "Username": "studenttesttwo",
        "Skills": [],
        "GPA": null,
        "Minor": null,
        "Last Name": "a",
        "Phone Number": null,
        "Extra-Cirriculars": [],
        "Account Type": "Student",
        "Password": "adam",
        "Email Address": null
    },
    {
        "Status": null,
        "Company": null,
        "Experiences": [
            {
                "Job Occupation": null,
                "Job Type": null,
                "Previous Experiences": null,
                "Job Length": null,
                "Job Desc": null
            }
        ],
        "First Name": null,
        "Concentration": null,
        "userid": "3643544b-392f-4a41-8d6f-440c4de44a92",
        "Grade Level": null,
        "School": null,
        "Major": null,
        "Username": "adamadmin",
        "Skills": [],
        "GPA": null,
        "Minor": null,
        "Last Name": null,
        "Phone Number": null,
        "Extra-Cirriculars": [],
        "Account Type": "Admin",
        "Password": "adam",
        "Email Address": null
    },
    {
        "Status": null,
        "Company": "Trickett",
        "Experiences": [
            {
                "Job Occupation": null,
                "Job Type": null,
                "Previous Experiences": null,
                "Job Length": null,
                "Job Desc": null
            }
        ],
        "First Name": null,
        "Concentration": null,
        "userid": "e43266e6-3407-417e-934e-a72ba427416c",
        "Grade Level": null,
        "School": "Adam",
        "Major": null,
        "Username": "adamrtrickett",
        "Skills": [
            "Swimming",
            "Python",
            "Rust",
            "PHP",
            "Yoga"
        ],
        "GPA": null,
        "Minor": null,
        "Last Name": null,
        "Phone Number": null,
        "Extra-Cirriculars": [
            "Club swimming",
            "Yoga Club",
            "Coding Club"
        ],
        "Account Type": "Student",
        "Password": "adampassword",
        "Email Address": null
    },
    {
        "Status": null,
        "Company": "a",
        "Experiences": [
            {
                "Job Occupation": null,
                "Job Type": null,
                "Previous Experiences": null,
                "Job Length": null,
                "Job Desc": null
            }
        ],
        "First Name": null,
        "Concentration": null,
        "userid": "a9c31424-0987-4c1e-b8a0-e8f8b4b4f3cd",
        "Grade Level": null,
        "School": "a",
        "Major": null,
        "Username": "a",
        "Skills": [],
        "GPA": null,
        "Minor": null,
        "Last Name": null,
        "Phone Number": null,
        "Extra-Cirriculars": [],
        "Account Type": "Student",
        "Password": "a",
        "Email Address": null
    },
    {
        "Status": null,
        "Company": null,
        "Experiences": [
            {
                "Job Occupation": null,
                "Job Type": null,
                "Previous Experiences": null,
                "Job Length": null,
                "Job Desc": null
            }
        ],
        "First Name": "first",
        "Concentration": null,
        "userid": "c0f9b2ed-e112-425c-93c0-0e6fd579bde5",
        "Grade Level": null,
        "School": null,
        "Major": null,
        "Username": "usernamee",
        "Skills": [
            "skill1",
            "skill2",
            "skill3"
        ],
        "GPA": null,
        "Minor": null,
        "Last Name": "last",
        "Phone Number": null,
        "Extra-Cirriculars": [
            "exc1",
            "exc2",
            "exc3"
        ],
        "Account Type": "Student",
        "Password": "password",
        "Email Address": null
    },
    {
        "Status": null,
        "Company": "Trickettcorp",
        "Experiences": [
            {
                "Job Occupation": null,
                "Job Type": null,
                "Previous Experiences": null,
                "Job Length": null,
                "Job Desc": null
            }
        ],
        "First Name": "Adam",
        "Concentration": null,
        "userid": "93e891bd-491b-4e77-8d53-d83b933a5ff4",
        "Grade Level": null,
        "School": null,
        "Major": null,
        "Username": "aemp",
        "Skills": [],
        "GPA": null,
        "Minor": null,
        "Last Name": "Trickett",
        "Phone Number": null,
        "Extra-Cirriculars": [],
        "Account Type": "Employer",
        "Password": "adam",
        "Email Address": null
    },
    {
        "Status": null,
        "Company": null,
        "Experiences": [
            {
                "Job Occupation": null,
                "Job Type": null,
                "Previous Experiences": null,
                "Job Length": null,
                "Job Desc": null
            }
        ],
        "First Name": "Brandon Jennings",
        "Concentration": null,
        "userid": "0878ba09-cc1b-41fd-b2a6-f03c528f41dd",
        "Grade Level": null,
        "School": null,
        "Major": null,
        "Username": "bj",
        "Skills": [],
        "GPA": null,
        "Minor": null,
        "Last Name": "Jennings",
        "Phone Number": "999-9999",
        "Extra-Cirriculars": [],
        "Account Type": "Student",
        "Password": "789",
        "Email Address": "rockstart@email.com"
    },
    {
        "Status": null,
        "Company": null,
        "Experiences": [
            {
                "Job Occupation": null,
                "Job Type": null,
                "Previous Experiences": null,
                "Job Length": null,
                "Job Desc": null
            }
        ],
        "First Name": "Brandon",
        "Concentration": null,
        "userid": "e6123673-03ca-40aa-b9cd-18f0b8c900c6",
        "Grade Level": null,
        "School": null,
        "Major": null,
        "Username": "Brandon",
        "Skills": [],
        "GPA": null,
        "Minor": null,
        "Last Name": "Jennings",
        "Phone Number": "999-9999",
        "Extra-Cirriculars": [],
        "Account Type": "Student",
        "Password": "456",
        "Email Address": "theotherguy@email.com"
    },
    {
        "Status": null,
        "Company": null,
        "Experiences": [
            {
                "Job Occupation": null,
                "Job Type": null,
                "Previous Experiences": null,
                "Job Length": null,
                "Job Desc": null
            }
        ],
        "First Name": null,
        "Concentration": null,
        "userid": "4df96278-e772-4e15-9608-bcbf3259e636",
        "Grade Level": null,
        "School": null,
        "Major": null,
        "Username": "adamad",
        "Skills": [],
        "GPA": null,
        "Minor": null,
        "Last Name": null,
        "Phone Number": null,
        "Extra-Cirriculars": [],
        "Account Type": "Admin",
        "Password": "adam",
        "Email Address": null
    },
    {
        "Status": null,
        "Company": null,
        "Experiences": [
            {
                "Job Occupation": null,
                "Job Type": null,
                "Previous Experiences": null,
                "Job Length": null,
                "Job Desc": null
            }
        ],
        "First Name": null,
        "Concentration": null,
        "userid": "441f4743-da83-456f-8e2b-d927ac5bd30e",
        "Grade Level": null,
        "School": null,
        "Major": null,
        "Username": "adamin",
        "Skills": [],
        "GPA": null,
        "Minor": null,
        "Last Name": null,
        "Phone Number": null,
        "Extra-Cirriculars": [],
        "Account Type": "Admin",
        "Password": "adam",
        "Email Address": null
    },
    {
        "Status": null,
        "Company": null,
        "Experiences": [
            {
                "Job Occupation": null,
                "Job Type": null,
                "Previous Experiences": null,
                "Job Length": null,
                "Job Desc": null
            }
        ],
        "First Name": "",
        "Concentration": null,
        "userid": "4cfcf0a4-61d2-464f-ae71-013137e49dcd",
        "Grade Level": null,
        "School": null,
        "Major": null,
        "Username": "adams",
        "Skills": [],
        "GPA": null,
        "Minor": null,
        "Last Name": "last",
        "Phone Number": "1234567890",
        "Extra-Cirriculars": [],
        "Account Type": "Student",
        "Password": "adam",
        "Email Address": "adam@mail.com"
    },
    {
        "Status": null,
        "Company": null,
        "Experiences": [
            {
                "Job Occupation": null,
                "Job Type": null,
                "Previous Experiences": null,
                "Job Length": null,
                "Job Desc": null
            }
        ],
        "First Name": "Adam",
        "Concentration": null,
        "userid": "852cc4eb-c1b7-4a44-9c12-091ab2de9dfe",
        "Grade Level": null,
        "School": null,
        "Major": null,
        "Username": "adamnew",
        "Skills": [
            "skill1",
            "skill2"
        ],
        "GPA": null,
        "Minor": null,
        "Last Name": "Trickett",
        "Phone Number": "1234567890",
        "Extra-Cirriculars": [
            "exc1",
            "exc2"
        ],
        "Account Type": "Student",
        "Password": "adam",
        "Email Address": "adam@mail.com"
    }
]