[
    {
        "Status": null,
        "Jobs Applied to": null,
        "Company": null,
        "Experiences": [
            {
                "Job Occupation": null,
                "Job Type": null,
                "Previous Experiences": null,
                "Job Length": null,
                "Job Desc": null
            }
        ],
        "First Name": null,
        "Concentration": null,
        "userid": "50d5b78a-71e3-48da-8fcb-574c690d506a",
        "Grade Level": null,
        "School": null,
        "Major": null,
        "Username": "JohnDoe_xd",
        "Skills": null,
        "GPA": null,
        "Minor": null,
        "Last Name": null,
        "Phone Number": null,
        "Extra-Cirriculars": null,
        "Account Type": "Administrator",
        "Password": "JavaIsCool",
        "Email Address": null
    },
    {
        "Status": "Unemployed",
        "Jobs Applied to": null,
        "Company": null,
        "Experiences": [
            {
                "Job Occupation": null,
                "Job Type": null,
                "Previous Experiences": null,
                "Job Length": null,
                "Job Desc": null
            }
        ],
        "First Name": "John",
        "Concentration": "Computer Science",
        "userid": "4acbdafb-fd48-4f04-a171-2a3b31aebfdd",
        "Grade Level": "Junior",
        "School": "University of South Carolina",
        "Major": "Computer Information Systems",
        "Username": "JackMiller",
        "Skills": [
            "Java",
            "mySQL",
            "C++",
            "MTA:Networking Fundamentals"
        ],
        "GPA": "3.4",
        "Minor": null,
        "Last Name": "Doe",
        "Phone Number": null,
        "Extra-Cirriculars": [
            "Robotics"
        ],
        "Account Type": "Student",
        "Password": "INeedAJob",
        "Email Address": null
    },
    {
        "Status": null,
        "Jobs Applied to": null,
        "Company": "Volt-tech",
        "Experiences": [
            {
                "Job Occupation": null,
                "Job Type": null,
                "Previous Experiences": null,
                "Job Length": null,
                "Job Desc": null
            }
        ],
        "First Name": null,
        "Concentration": null,
        "userid": "b3097086-65c8-4bf1-9d49-f128da514457",
        "Grade Level": null,
        "School": null,
        "Major": null,
        "Username": "JeffreySmith",
        "Skills": null,
        "GPA": null,
        "Minor": null,
        "Last Name": null,
        "Phone Number": null,
        "Extra-Cirriculars": null,
        "Account Type": "Employer",
        "Password": "needNewHires!",
        "Email Address": null
    },
    {
        "Status": null,
        "Jobs Applied to": null,
        "Company": null,
        "Experiences": [
            {
                "Job Occupation": null,
                "Job Type": null,
                "Previous Experiences": null,
                "Job Length": null,
                "Job Desc": null
            }
        ],
        "First Name": null,
        "Concentration": null,
        "userid": "b40a9d02-596b-4cdd-8be1-65132f36d44d",
        "Grade Level": null,
        "School": null,
        "Major": null,
        "Username": "bjj",
        "Skills": null,
        "GPA": null,
        "Minor": null,
        "Last Name": null,
        "Phone Number": "999-9999",
        "Extra-Cirriculars": null,
        "Account Type": "Student",
        "Password": "dfsfafasd",
        "Email Address": "btj2@email.sc.edu"
    },
    {
        "Status": null,
        "Jobs Applied to": null,
        "Company": null,
        "Experiences": [
            {
                "Job Occupation": null,
                "Job Type": null,
                "Previous Experiences": null,
                "Job Length": null,
                "Job Desc": null
            }
        ],
        "First Name": null,
        "Concentration": null,
        "userid": "c6aa71c2-2f58-40af-86c8-29bb39a6bf87",
        "Grade Level": null,
        "School": null,
        "Major": null,
        "Username": "brady smoak",
        "Skills": null,
        "GPA": null,
        "Minor": null,
        "Last Name": null,
        "Phone Number": "999-9999",
        "Extra-Cirriculars": null,
        "Account Type": "Student",
        "Password": "celtics rule",
        "Email Address": "btj2@email.sc.edu"
    },
    {
        "Status": null,
        "Jobs Applied to": null,
        "Company": null,
        "Experiences": [
            {
                "Job Occupation": null,
                "Job Type": null,
                "Previous Experiences": null,
                "Job Length": null,
                "Job Desc": null
            }
        ],
        "First Name": "brandon",
        "Concentration": "CS",
        "userid": "529bb16d-ea29-4dcb-a509-55dc302a4818",
        "Grade Level": "senior",
        "School": "u of sc",
        "Major": "CIS",
        "Username": "brandon",
        "Skills": [],
        "GPA": "3.8",
        "Minor": "BIM",
        "Last Name": "jennings",
        "Phone Number": "999-9999",
        "Extra-Cirriculars": [],
        "Account Type": "Student",
        "Password": "1234",
        "Email Address": "rockstar@email.com"
    },
    {
        "Status": null,
        "Jobs Applied to": null,
        "Company": "brandon",
        "Experiences": [
            {
                "Job Occupation": null,
                "Job Type": null,
                "Previous Experiences": null,
                "Job Length": null,
                "Job Desc": null
            }
        ],
        "First Name": null,
        "Concentration": null,
        "userid": "67c64605-7d2e-414c-8720-5eb67b72f21f",
        "Grade Level": null,
        "School": null,
        "Major": null,
        "Username": "btj",
        "Skills": null,
        "GPA": null,
        "Minor": null,
        "Last Name": "jennings",
        "Phone Number": null,
        "Extra-Cirriculars": null,
        "Account Type": "Student",
        "Password": "1234",
        "Email Address": null
    },
    {
        "Status": null,
        "Jobs Applied to": null,
        "Company": null,
        "Experiences": [
            {
                "Job Occupation": null,
                "Job Type": null,
                "Previous Experiences": null,
                "Job Length": null,
                "Job Desc": null
            }
        ],
        "First Name": "adam",
        "Concentration": "a",
        "userid": "4d2b4b8e-15f3-41b5-bcf8-f8be16bed05a",
        "Grade Level": "a",
        "School": "a",
        "Major": "a",
        "Username": "adamrt",
        "Skills": null,
        "GPA": "a",
        "Minor": "a",
        "Last Name": "a",
        "Phone Number": null,
        "Extra-Cirriculars": null,
        "Account Type": "Student",
        "Password": "adam",
        "Email Address": null
    },
    {
        "Status": null,
        "Jobs Applied to": null,
        "Company": null,
        "Experiences": [
            {
                "Job Occupation": null,
                "Job Type": null,
                "Previous Experiences": null,
                "Job Length": null,
                "Job Desc": null
            }
        ],
        "First Name": "adam",
        "Concentration": "a",
        "userid": "ae98fd70-2a40-4df0-8d2d-d80fd782dc79",
        "Grade Level": "a",
        "School": "a",
        "Major": "a",
        "Username": "adamrt",
        "Skills": null,
        "GPA": "a",
        "Minor": "a",
        "Last Name": "a",
        "Phone Number": null,
        "Extra-Cirriculars": null,
        "Account Type": "Student",
        "Password": "adam",
        "Email Address": null
    },
    {
        "Status": null,
        "Jobs Applied to": null,
        "Company": null,
        "Experiences": [
            {
                "Job Occupation": null,
                "Job Type": null,
                "Previous Experiences": null,
                "Job Length": null,
                "Job Desc": null
            }
        ],
        "First Name": "adam",
        "Concentration": null,
        "userid": "b4f18c34-5794-441d-9474-e70cb0fcc7c7",
        "Grade Level": null,
        "School": null,
        "Major": null,
        "Username": "aaaaaaa",
        "Skills": null,
        "GPA": null,
        "Minor": null,
        "Last Name": "adam",
        "Phone Number": null,
        "Extra-Cirriculars": null,
        "Account Type": "Student",
        "Password": "adam",
        "Email Address": null
    },
    {
        "Status": null,
        "Jobs Applied to": null,
        "Company": null,
        "Experiences": [
            {
                "Job Occupation": null,
                "Job Type": null,
                "Previous Experiences": null,
                "Job Length": null,
                "Job Desc": null
            }
        ],
        "First Name": null,
        "Concentration": null,
        "userid": "80e8c619-1954-4bab-97d1-2b4cd88f6b18",
        "Grade Level": null,
        "School": null,
        "Major": null,
        "Username": "employerman",
        "Skills": null,
        "GPA": null,
        "Minor": null,
        "Last Name": null,
        "Phone Number": null,
        "Extra-Cirriculars": null,
        "Account Type": "Employer",
        "Password": "adam",
        "Email Address": null
    },
    {
        "Status": null,
        "Jobs Applied to": null,
        "Company": null,
        "Experiences": [
            {
                "Job Occupation": null,
                "Job Type": null,
                "Previous Experiences": null,
                "Job Length": null,
                "Job Desc": null
            }
        ],
        "First Name": "Adam",
        "Concentration": null,
        "userid": "11b57f86-75f6-407f-a788-61dccf88e966",
        "Grade Level": null,
        "School": null,
        "Major": null,
        "Username": "adammmm",
        "Skills": null,
        "GPA": null,
        "Minor": null,
        "Last Name": "Trickett",
        "Phone Number": null,
        "Extra-Cirriculars": null,
        "Account Type": "Student",
        "Password": "adam",
        "Email Address": null
    },
    {
        "Status": null,
        "Jobs Applied to": null,
        "Company": null,
        "Experiences": [
            {
                "Job Occupation": null,
                "Job Type": null,
                "Previous Experiences": null,
                "Job Length": null,
                "Job Desc": null
            }
        ],
        "First Name": null,
        "Concentration": null,
        "userid": "ea80b1cb-09b4-4eef-9d98-f569e1a56afb",
        "Grade Level": null,
        "School": null,
        "Major": null,
        "Username": "adamemp",
        "Skills": [],
        "GPA": null,
        "Minor": null,
        "Last Name": null,
        "Phone Number": null,
        "Extra-Cirriculars": [],
        "Account Type": "Employer",
        "Password": "adam",
        "Email Address": null
    },
    {
        "Status": null,
        "Jobs Applied to": null,
        "Company": null,
        "Experiences": [
            {
                "Job Occupation": null,
                "Job Type": null,
                "Previous Experiences": null,
                "Job Length": null,
                "Job Desc": null
            }
        ],
        "First Name": null,
        "Concentration": null,
        "userid": "970ea63b-3981-4c0a-b8b5-1b120587841c",
        "Grade Level": null,
        "School": null,
        "Major": null,
        "Username": "adamwork",
        "Skills": [],
        "GPA": null,
        "Minor": null,
        "Last Name": null,
        "Phone Number": null,
        "Extra-Cirriculars": [],
        "Account Type": "Employer",
        "Password": "adam",
        "Email Address": null
    },
    {
        "Status": null,
        "Jobs Applied to": null,
        "Company": "adamco",
        "Experiences": [
            {
                "Job Occupation": null,
                "Job Type": null,
                "Previous Experiences": null,
                "Job Length": null,
                "Job Desc": null
            }
        ],
        "First Name": "adam",
        "Concentration": null,
        "userid": "7a5620ed-8bef-4471-8385-4c59e3b5aef2",
        "Grade Level": null,
        "School": null,
        "Major": null,
        "Username": "adamusername",
        "Skills": [],
        "GPA": null,
        "Minor": null,
        "Last Name": "trickett",
        "Phone Number": null,
        "Extra-Cirriculars": [],
        "Account Type": "Employer",
        "Password": "adampassword",
        "Email Address": null
    },
    {
        "Status": null,
        "Jobs Applied to": null,
        "Company": "Trickett",
        "Experiences": [
            {
                "Job Occupation": null,
                "Job Type": null,
                "Previous Experiences": null,
                "Job Length": null,
                "Job Desc": null
            }
        ],
        "First Name": null,
        "Concentration": null,
        "userid": "82f89737-2737-4c5d-96cb-f8e3adb37712",
        "Grade Level": null,
        "School": "Adam",
        "Major": null,
        "Username": "adamstudent",
        "Skills": [
            "Python",
            "Java",
            "C++",
            "Window cleaning",
            "Floor cleaning"
        ],
        "GPA": null,
        "Minor": null,
        "Last Name": null,
        "Phone Number": null,
        "Extra-Cirriculars": [
            "Cleaning club",
            "Coding club",
            ""
        ],
        "Account Type": "Student",
        "Password": "adam",
        "Email Address": null
    },
    {
        "Status": null,
        "Jobs Applied to": null,
        "Company": "trickett",
        "Experiences": [
            {
                "Job Occupation": null,
                "Job Type": null,
                "Previous Experiences": null,
                "Job Length": null,
                "Job Desc": null
            }
        ],
        "First Name": null,
        "Concentration": null,
        "userid": "2dedf7a7-de67-4d66-a8e0-f3f29759b13f",
        "Grade Level": null,
        "School": "adam",
        "Major": null,
        "Username": "studenttest",
        "Skills": [
            "counseling"
        ],
        "GPA": null,
        "Minor": null,
        "Last Name": null,
        "Phone Number": null,
        "Extra-Cirriculars": [
            "camping"
        ],
        "Account Type": "Student",
        "Password": "adam",
        "Email Address": null
    },
    {
        "Status": null,
        "Jobs Applied to": null,
        "Company": null,
        "Experiences": [
            {
                "Job Occupation": null,
                "Job Type": null,
                "Previous Experiences": null,
                "Job Length": null,
                "Job Desc": null
            }
        ],
        "First Name": "a",
        "Concentration": null,
        "userid": "3b0e413b-2bba-49cf-afb5-6dd815c8e62b",
        "Grade Level": null,
        "School": null,
        "Major": null,
        "Username": "1",
        "Skills": [],
        "GPA": null,
        "Minor": null,
        "Last Name": "a",
        "Phone Number": null,
        "Extra-Cirriculars": [],
        "Account Type": "Student",
        "Password": "a",
        "Email Address": null
    },
    {
        "Status": null,
        "Jobs Applied to": null,
        "Company": null,
        "Experiences": [
            {
                "Job Occupation": null,
                "Job Type": null,
                "Previous Experiences": null,
                "Job Length": null,
                "Job Desc": null
            }
        ],
        "First Name": "a",
        "Concentration": null,
        "userid": "e2bef686-84df-4744-a15c-3f98b660e199",
        "Grade Level": null,
        "School": null,
        "Major": null,
        "Username": "studenttesttwo",
        "Skills": [],
        "GPA": null,
        "Minor": null,
        "Last Name": "a",
        "Phone Number": null,
        "Extra-Cirriculars": [],
        "Account Type": "Student",
        "Password": "adam",
        "Email Address": null
    },
    {
        "Status": null,
        "Jobs Applied to": null,
        "Company": null,
        "Experiences": [
            {
                "Job Occupation": null,
                "Job Type": null,
                "Previous Experiences": null,
                "Job Length": null,
                "Job Desc": null
            }
        ],
        "First Name": null,
        "Concentration": null,
        "userid": "5933ae30-7066-4296-8e58-622969c05913",
        "Grade Level": null,
        "School": null,
        "Major": null,
        "Username": "adamadmin",
        "Skills": [],
        "GPA": null,
        "Minor": null,
        "Last Name": null,
        "Phone Number": null,
        "Extra-Cirriculars": [],
        "Account Type": "Admin",
        "Password": "adam",
        "Email Address": null
    },
    {
        "Status": null,
        "Jobs Applied to": null,
        "Company": "Trickett",
        "Experiences": [
            {
                "Job Occupation": null,
                "Job Type": null,
                "Previous Experiences": null,
                "Job Length": null,
                "Job Desc": null
            }
        ],
        "First Name": null,
        "Concentration": null,
        "userid": "470ef91c-9d93-4907-9689-cbb31f10294f",
        "Grade Level": null,
        "School": "Adam",
        "Major": null,
        "Username": "adamrtrickett",
        "Skills": [
            "Swimming",
            "Python",
            "Rust",
            "PHP",
            "Yoga"
        ],
        "GPA": null,
        "Minor": null,
        "Last Name": null,
        "Phone Number": null,
        "Extra-Cirriculars": [
            "Club swimming",
            "Yoga Club",
            "Coding Club"
        ],
        "Account Type": "Student",
        "Password": "adampassword",
        "Email Address": null
    },
    {
        "Status": null,
        "Jobs Applied to": null,
        "Company": "a",
        "Experiences": [
            {
                "Job Occupation": null,
                "Job Type": null,
                "Previous Experiences": null,
                "Job Length": null,
                "Job Desc": null
            }
        ],
        "First Name": null,
        "Concentration": null,
        "userid": "608b8061-e4f3-44a4-bf31-3e399b3e463b",
        "Grade Level": null,
        "School": "a",
        "Major": null,
        "Username": "a",
        "Skills": [],
        "GPA": null,
        "Minor": null,
        "Last Name": null,
        "Phone Number": null,
        "Extra-Cirriculars": [],
        "Account Type": "Student",
        "Password": "a",
        "Email Address": null
    },
    {
        "Status": null,
        "Jobs Applied to": null,
        "Company": null,
        "Experiences": [
            {
                "Job Occupation": null,
                "Job Type": null,
                "Previous Experiences": null,
                "Job Length": null,
                "Job Desc": null
            }
        ],
        "First Name": "first",
        "Concentration": null,
        "userid": "68dfe94a-c42b-4d96-8d25-fafcb00a05ac",
        "Grade Level": null,
        "School": null,
        "Major": null,
        "Username": "usernamee",
        "Skills": [
            "skill1",
            "skill2",
            "skill3"
        ],
        "GPA": null,
        "Minor": null,
        "Last Name": "last",
        "Phone Number": null,
        "Extra-Cirriculars": [
            "exc1",
            "exc2",
            "exc3"
        ],
        "Account Type": "Student",
        "Password": "password",
        "Email Address": null
    },
    {
        "Status": null,
        "Jobs Applied to": null,
        "Company": "Trickettcorp",
        "Experiences": [
            {
                "Job Occupation": null,
                "Job Type": null,
                "Previous Experiences": null,
                "Job Length": null,
                "Job Desc": null
            }
        ],
        "First Name": "Adam",
        "Concentration": null,
        "userid": "cc9fdddc-fee2-40a8-9010-8288c85ba18f",
        "Grade Level": null,
        "School": null,
        "Major": null,
        "Username": "aemp",
        "Skills": [],
        "GPA": null,
        "Minor": null,
        "Last Name": "Trickett",
        "Phone Number": null,
        "Extra-Cirriculars": [],
        "Account Type": "Employer",
        "Password": "adam",
        "Email Address": null
    },
    {
        "Status": null,
        "Jobs Applied to": null,
        "Company": null,
        "Experiences": [
            {
                "Job Occupation": null,
                "Job Type": null,
                "Previous Experiences": null,
                "Job Length": null,
                "Job Desc": null
            }
        ],
        "First Name": "Brandon Jennings",
        "Concentration": null,
        "userid": "68563fee-ab7d-4339-a7e4-9ce85659c956",
        "Grade Level": null,
        "School": null,
        "Major": null,
        "Username": "bj",
        "Skills": [],
        "GPA": null,
        "Minor": null,
        "Last Name": "Jennings",
        "Phone Number": "999-9999",
        "Extra-Cirriculars": [],
        "Account Type": "Student",
        "Password": "789",
        "Email Address": "rockstart@email.com"
    },
    {
        "Status": null,
        "Jobs Applied to": null,
        "Company": null,
        "Experiences": [
            {
                "Job Occupation": null,
                "Job Type": null,
                "Previous Experiences": null,
                "Job Length": null,
                "Job Desc": null
            }
        ],
        "First Name": "Brandon",
        "Concentration": null,
        "userid": "a11c34a7-8d37-4b3b-8b28-7eedab2d5cee",
        "Grade Level": null,
        "School": null,
        "Major": null,
        "Username": "Brandon",
        "Skills": [],
        "GPA": null,
        "Minor": null,
        "Last Name": "Jennings",
        "Phone Number": "999-9999",
        "Extra-Cirriculars": [],
        "Account Type": "Student",
        "Password": "456",
        "Email Address": "theotherguy@email.com"
    },
    {
        "Status": null,
        "Jobs Applied to": null,
        "Company": null,
        "Experiences": [
            {
                "Job Occupation": null,
                "Job Type": null,
                "Previous Experiences": null,
                "Job Length": null,
                "Job Desc": null
            }
        ],
        "First Name": null,
        "Concentration": null,
        "userid": "17f20b46-6b5c-45b5-bfa4-f5a42034bc32",
        "Grade Level": null,
        "School": null,
        "Major": null,
        "Username": "adamad",
        "Skills": [],
        "GPA": null,
        "Minor": null,
        "Last Name": null,
        "Phone Number": null,
        "Extra-Cirriculars": [],
        "Account Type": "Admin",
        "Password": "adam",
        "Email Address": null
    },
    {
        "Status": null,
        "Jobs Applied to": null,
        "Company": null,
        "Experiences": [
            {
                "Job Occupation": null,
                "Job Type": null,
                "Previous Experiences": null,
                "Job Length": null,
                "Job Desc": null
            }
        ],
        "First Name": null,
        "Concentration": null,
        "userid": "b06a0c8a-7988-4dbd-8b75-4ad4e8b43afa",
        "Grade Level": null,
        "School": null,
        "Major": null,
        "Username": "adamin",
        "Skills": [],
        "GPA": null,
        "Minor": null,
        "Last Name": null,
        "Phone Number": null,
        "Extra-Cirriculars": [],
        "Account Type": "Admin",
        "Password": "adam",
        "Email Address": null
    },
    {
        "Status": null,
        "Jobs Applied to": null,
        "Company": null,
        "Experiences": [
            {
                "Job Occupation": null,
                "Job Type": null,
                "Previous Experiences": null,
                "Job Length": null,
                "Job Desc": null
            }
        ],
        "First Name": "",
        "Concentration": null,
        "userid": "757d6edf-a680-4b6c-b525-fbb193970d41",
        "Grade Level": null,
        "School": null,
        "Major": null,
        "Username": "adams",
        "Skills": [],
        "GPA": null,
        "Minor": null,
        "Last Name": "last",
        "Phone Number": "1234567890",
        "Extra-Cirriculars": [],
        "Account Type": "Student",
        "Password": "adam",
        "Email Address": "adam@mail.com"
    },
    {
        "Status": null,
        "Jobs Applied to": null,
        "Company": null,
        "Experiences": [
            {
                "Job Occupation": null,
                "Job Type": null,
                "Previous Experiences": null,
                "Job Length": null,
                "Job Desc": null
            }
        ],
        "First Name": "Adam",
        "Concentration": null,
        "userid": "8e432f03-bd94-4344-bd5a-c37e07b97471",
        "Grade Level": null,
        "School": null,
        "Major": null,
        "Username": "adamnew",
        "Skills": [
            "skill1",
            "skill2"
        ],
        "GPA": null,
        "Minor": null,
        "Last Name": "Trickett",
        "Phone Number": "1234567890",
        "Extra-Cirriculars": [
            "exc1",
            "exc2"
        ],
        "Account Type": "Student",
        "Password": "adam",
        "Email Address": "adam@mail.com"
    },
    {
        "Status": null,
        "Jobs Applied to": null,
        "Company": null,
        "Experiences": [
            {
                "Job Occupation": null,
                "Job Type": null,
                "Previous Experiences": null,
                "Job Length": null,
                "Job Desc": null
            }
        ],
        "First Name": "Adam",
        "Concentration": null,
        "userid": "2780b9f8-30b7-4c5a-a951-967db2217780",
        "Grade Level": null,
        "School": null,
        "Major": null,
        "Username": "adamnewnew",
        "Skills": [],
        "GPA": null,
        "Minor": null,
        "Last Name": "Trickett",
        "Phone Number": "123-456-7890",
        "Extra-Cirriculars": [],
        "Account Type": "Student",
        "Password": "adam",
        "Email Address": "email@email.com"
    },
    {
        "Status": null,
        "Jobs Applied to": null,
        "Company": "adamco",
        "Experiences": [
            {
                "Job Occupation": null,
                "Job Type": null,
                "Previous Experiences": null,
                "Job Length": null,
                "Job Desc": null
            }
        ],
        "First Name": "Adam",
        "Concentration": null,
        "userid": "9bdf893a-e1b1-49e5-a910-772e7e0020f6",
        "Grade Level": null,
        "School": null,
        "Major": null,
        "Username": "adamemploy",
        "Skills": [],
        "GPA": null,
        "Minor": null,
        "Last Name": "Trickett",
        "Phone Number": null,
        "Extra-Cirriculars": [],
        "Account Type": "Employer",
        "Password": "adam",
        "Email Address": null
    },
    {
        "Status": null,
        "Jobs Applied to": null,
        "Company": null,
        "Experiences": [
            {
                "Job Occupation": null,
                "Job Type": null,
                "Previous Experiences": null,
                "Job Length": null,
                "Job Desc": null
            }
        ],
        "First Name": "first",
        "Concentration": null,
        "userid": "a3c95664-9a8a-4922-b67c-b0cf47b3a639",
        "Grade Level": null,
        "School": null,
        "Major": null,
        "Username": "usernames",
        "Skills": [
            "skill1",
            "skill2",
            "skilll3"
        ],
        "GPA": null,
        "Minor": null,
        "Last Name": "last",
        "Phone Number": "phone",
        "Extra-Cirriculars": [
            "exc1",
            "exc2",
            "exc3"
        ],
        "Account Type": "Student",
        "Password": "password",
        "Email Address": "email"
    },
    {
        "Status": null,
        "Jobs Applied to": [],
        "Company": null,
        "Experiences": [
            {
                "Job Occupation": "associate",
                "Job Type": "parttime",
                "Previous Experiences": "officemax",
                "Job Length": "present",
                "Job Desc": "sell stuff"
            }
        ],
        "First Name": "dak",
        "Concentration": "CS",
        "userid": "6b824f2b-3f89-48b2-8d5f-099190c28ada",
        "Grade Level": "Senior",
        "School": "u of sc",
        "Major": "CIS",
        "Username": "dak",
        "Skills": [
            "java",
            "c++",
            "sql"
        ],
        "GPA": "3.8",
        "Minor": "BIM",
        "Last Name": "prescott",
        "Phone Number": "999-9999",
        "Extra-Cirriculars": [
            "football",
            "baseball"
        ],
        "Account Type": "Student",
        "Password": "prescott",
        "Email Address": "email"
    }
]